nml_lz77.cpython-310-darwin.so
nml/grfstrings.py
nml/version_info.py
nml/spriteencoder.py
nml/version_update.py
nml/global_constants.py
nml/generic.py
nml/output_base.py
nml/output_dep.py
nml/__init__.py
nml/__version__.py
nml/tokens.py
nml/nmlop.py
nml/palette.py
nml/parser.py
nml/free_number_list.py
nml/unit.py
nml/spritecache.py
nml/lz77.py
nml/output_nfo.py
nml/output_grf.py
nml/main.py
nml/output_nml.py
nml/ply/yacc.py
nml/ply/lex.py
nml/ply/__init__.py
nml/editors/notepadpp.py
nml/editors/kate.py
nml/editors/__init__.py
nml/editors/extract_tables.py
nml/editors/visualstudiocode.py
nml/actions/action3.py
nml/actions/sprite_count.py
nml/actions/actionD.py
nml/actions/action2var_variables.py
nml/actions/action2production.py
nml/actions/action7.py
nml/actions/action0properties.py
nml/actions/action6.py
nml/actions/actionA.py
nml/actions/action3_callbacks.py
nml/actions/action2.py
nml/actions/action12.py
nml/actions/actionE.py
nml/actions/__init__.py
nml/actions/action8.py
nml/actions/action2var.py
nml/actions/base_action.py
nml/actions/real_sprite.py
nml/actions/action5.py
nml/actions/action2random.py
nml/actions/actionB.py
nml/actions/action1.py
nml/actions/action11.py
nml/actions/actionF.py
nml/actions/action0.py
nml/actions/action2real.py
nml/actions/action10.py
nml/actions/action4.py
nml/actions/action2layout.py
nml/actions/action14.py
nml/ast/spriteblock.py
nml/ast/tracktypetable.py
nml/ast/produce.py
nml/ast/snowline.py
nml/ast/base_graphics.py
nml/ast/error.py
nml/ast/townnames.py
nml/ast/alt_sprites.py
nml/ast/__init__.py
nml/ast/sprite_container.py
nml/ast/cargotable.py
nml/ast/font.py
nml/ast/switch.py
nml/ast/deactivate.py
nml/ast/tilelayout.py
nml/ast/grf.py
nml/ast/disable_item.py
nml/ast/basecost.py
nml/ast/loop.py
nml/ast/assignment.py
nml/ast/base_statement.py
nml/ast/sort_vehicles.py
nml/ast/constant.py
nml/ast/conditional.py
nml/ast/skipall.py
nml/ast/item.py
nml-0.8.0.dist-info/RECORD
nml-0.8.0.dist-info/WHEEL
nml-0.8.0.dist-info/entry_points.txt
nml-0.8.0.dist-info/top_level.txt
nml-0.8.0.dist-info/METADATA
nml-0.8.0.dist-info/licenses/LICENSE
